django_cbias_auth/__init__.py
django_cbias_auth/apps.py
django_cbias_auth/management/commands/createoauthapp.py
django_cbias_auth/schema/__init__.py
django_cbias_auth/schema/mutations.py
django_cbias_auth/schema/types.py
django_cbias_auth/tests/__init__.py
django_cbias_auth/tests/command_tests.py
django_cbias_auth/tests/util_tests.py
django_cbias_auth/utils.py
django_cbias_auth-0.1.3.dist-info/LICENSE
django_cbias_auth-0.1.3.dist-info/WHEEL
django_cbias_auth-0.1.3.dist-info/METADATA
django_cbias_auth-0.1.3.dist-info/RECORD
