Metadata-Version: 2.1
Name: django-cbias-auth
Version: 0.1.3
Summary: Auth library via https://cbias.ru
Home-page: https://github.com/devind-team/django-cbias-auth
License: MIT
Keywords: django,graphene,auth
Author: devind-team
Author-email: team@devind.ru
Requires-Python: >=3.9,<4.0
Classifier: Framework :: Django
Classifier: License :: OSI Approved :: MIT License
Classifier: Operating System :: OS Independent
Classifier: Programming Language :: Python :: 3
Classifier: Programming Language :: Python :: 3.10
Classifier: Programming Language :: Python :: 3.9
Requires-Dist: Django (>=3.2.12,<5.0.0)
Requires-Dist: django-oauth-toolkit (>=1.7.0,<2.0.0)
Requires-Dist: graphene (==2.1.9)
Requires-Dist: graphene-django (>=2.15.0,<3.0.0)
Requires-Dist: requests (>=2.27.1,<3.0.0)
Project-URL: Repository, https://github.com/devind-team/django-cbias-auth
